xml_from_seq.py
xml_from_seq-0.3.3.dist-info/METADATA
xml_from_seq-0.3.3.dist-info/WHEEL
xml_from_seq-0.3.3.dist-info/top_level.txt
xml_from_seq-0.3.3.dist-info/RECORD
