Metadata-Version: 2.1
Name: xml_from_seq
Version: 0.3.3
Summary: Generate XML from Python data structure
Home-page: https://github.com/Media-Platforms/xml_from_seq
Author: Nic Wolff
Author-email: nwolff@hearst.com
License: MIT
Classifier: Programming Language :: Python :: 3
Classifier: License :: OSI Approved :: MIT License
Classifier: Operating System :: OS Independent
